UiComparePicRec/__init__.py
UiComparePicRec/example.py
UiComparePicRec/findHander.py
UiComparePicRec/picHander.py
UiComparePicRec-1.1.1.dist-info/LICENSE
UiComparePicRec-1.1.1.dist-info/METADATA
UiComparePicRec-1.1.1.dist-info/WHEEL
UiComparePicRec-1.1.1.dist-info/top_level.txt
UiComparePicRec-1.1.1.dist-info/RECORD
