Metadata-Version: 2.1
Name: UiComparePicRec
Version: 1.1.1
Summary: Selenium plugin library
Home-page: https://github.com/lijishuang/UI-Pic-Rec
Author: Jishuang Li
Author-email: 1103192570@qq.com
License: UNKNOWN
Platform: UNKNOWN
Classifier: Programming Language :: Python :: 3
Classifier: License :: OSI Approved :: GNU Affero General Public License v3 or later (AGPLv3+)
Classifier: Operating System :: OS Independent
